djangobible/__init__.py
djangobible/apps.py
djangobible/fields.py
djangobible/migrations/0001_initial.py
djangobible/migrations/__init__.py
djangobible/models.py
djangobible/templatetags/__init__.py
djangobible/templatetags/verse_tags.py
djangobible/validators.py
djangobible-0.3.0.dist-info/WHEEL
djangobible-0.3.0.dist-info/METADATA
djangobible-0.3.0.dist-info/RECORD
